setup.py
chessil_tourney_inserter/__init__.py
chessil_tourney_inserter/chessil_tourney_inserter.py
chessil_tourney_inserter/command_line.py
chessil_tourney_inserter/swiss98_text_parser.py
chessil_tourney_inserter.egg-info/PKG-INFO
chessil_tourney_inserter.egg-info/SOURCES.txt
chessil_tourney_inserter.egg-info/dependency_links.txt
chessil_tourney_inserter.egg-info/entry_points.txt
chessil_tourney_inserter.egg-info/not-zip-safe
chessil_tourney_inserter.egg-info/requires.txt
chessil_tourney_inserter.egg-info/top_level.txt