Metadata-Version: 1.0
Name: chessil-tourney-inserter
Version: 1.2.3
Summary: Uploads tournament data to Israel's chess federation site from SwissPerfect 98 generated SPDE files
Home-page: http://github.com/unc0mm0n/chessil_tourney_inserter
Author: Yuval Wyborski
Author-email: yvw.bor@gmail.com
License: UNKNOWN
Platform: UNKNOWN
